kadai/__init__.py
kadai/__main__.py
kadai/config_handler.py
kadai/log.py
kadai/themer.py
kadai/data/template.json
kadai/engine/__init__.py
kadai/engine/genhue.py
kadai/engine/k_means.py
kadai/engine/vibrance.py
kadai/utils/ColorUtils.py
kadai/utils/FileUtils.py
kadai/utils/__init__.py
KADAI-1.0.0rc2.dist-info/LICENSE
KADAI-1.0.0rc2.dist-info/METADATA
KADAI-1.0.0rc2.dist-info/WHEEL
KADAI-1.0.0rc2.dist-info/entry_points.txt
KADAI-1.0.0rc2.dist-info/top_level.txt
KADAI-1.0.0rc2.dist-info/RECORD
