Metadata-Version: 2.1
Name: KADAI
Version: 1.0.0rc2
Summary: Simple wallpaper manager for tiling window managers.
Home-page: http://github.com/slapelachie/kadai
Author: slapelachie
Author-email: slapelachie@gmail.com
License: GPLv2
Platform: UNKNOWN
Classifier: Development Status :: 4 - Beta
Classifier: Environment :: X11 Applications
Classifier: License :: OSI Approved :: GNU General Public License v2 (GPLv2)
Classifier: Natural Language :: English
Classifier: Operating System :: POSIX :: Linux
Classifier: Programming Language :: Python :: 3.8
Requires-Dist: Pillow
Requires-Dist: tqdm
Requires-Dist: colorthief
